napari_wsi/__init__.py
napari_wsi/color_transform.py
napari_wsi/common.py
napari_wsi/napari.yaml
napari_wsi/py.typed
napari_wsi/reader.py
napari_wsi/widget.py
napari_wsi/backends/__init__.py
napari_wsi/backends/common.py
napari_wsi/backends/openslide.py
napari_wsi/backends/rasterio.py
napari_wsi/backends/wsidicom.py
napari_wsi-1.2.1.dist-info/METADATA
napari_wsi-1.2.1.dist-info/WHEEL
napari_wsi-1.2.1.dist-info/entry_points.txt
napari_wsi-1.2.1.dist-info/licenses/LICENSE
napari_wsi-1.2.1.dist-info/RECORD
