Metadata-Version: 2.4
Name: napari-wsi
Version: 1.2.1
Summary: A plugin to read whole-slide images within napari.
Project-URL: Repository, https://github.com/AstraZeneca/napari-wsi
Author-email: Philipp Plewa <philipp.plewa@astrazeneca.com>
Maintainer-email: Philipp Plewa <philipp.plewa@astrazeneca.com>, Robert Schweizer <robert.schweizer@astrazeneca.com>
License-Expression: Apache-2.0
License-File: LICENSE
Classifier: Framework :: napari
Classifier: Intended Audience :: Developers
Classifier: Operating System :: OS Independent
Classifier: Topic :: Scientific/Engineering :: Image Processing
Requires-Python: >=3.11
Requires-Dist: dask>=2025.1
Requires-Dist: magicgui>=0.10
Requires-Dist: numpy>=1.26
Requires-Dist: pillow>=11.1
Requires-Dist: typing-extensions>=4.6.1
Requires-Dist: universal-pathlib>=0.2
Requires-Dist: zarr>=3.0
Provides-Extra: all
Requires-Dist: colorspacious>=1.1.2; extra == 'all'
Requires-Dist: openslide-python>=1.4; extra == 'all'
Requires-Dist: pandas>=2.0; extra == 'all'
Requires-Dist: rasterio>=1.4; extra == 'all'
Requires-Dist: shapely>=2.0; extra == 'all'
Requires-Dist: wsidicom>=0.22; extra == 'all'
Provides-Extra: openslide
Requires-Dist: openslide-python>=1.4; extra == 'openslide'
Provides-Extra: rasterio
Requires-Dist: rasterio>=1.4; extra == 'rasterio'
Provides-Extra: wsidicom
Requires-Dist: colorspacious>=1.1.2; extra == 'wsidicom'
Requires-Dist: pandas>=2.0; extra == 'wsidicom'
Requires-Dist: shapely>=2.0; extra == 'wsidicom'
Requires-Dist: wsidicom>=0.22; extra == 'wsidicom'
